keeper_secrets_manager_storage_gcp_kms/__init__.py
keeper_secrets_manager_storage_gcp_kms/constants.py
keeper_secrets_manager_storage_gcp_kms/enum.py
keeper_secrets_manager_storage_gcp_kms/kms_client.py
keeper_secrets_manager_storage_gcp_kms/kms_key_config.py
keeper_secrets_manager_storage_gcp_kms/storage_gcp_kms.py
keeper_secrets_manager_storage_gcp_kms/util_options.py
keeper_secrets_manager_storage_gcp_kms/utils.py
keeper_secrets_manager_storage_gcp_kms-1.0.1.dist-info/licenses/LICENSE
keeper_secrets_manager_storage_gcp_kms-1.0.1.dist-info/METADATA
keeper_secrets_manager_storage_gcp_kms-1.0.1.dist-info/WHEEL
keeper_secrets_manager_storage_gcp_kms-1.0.1.dist-info/top_level.txt
keeper_secrets_manager_storage_gcp_kms-1.0.1.dist-info/RECORD
