Metadata-Version: 2.4
Name: keeper-secrets-manager-storage-gcp-kms
Version: 1.0.1
Summary: Keeper Secrets Manager SDK storage integration with Google Cloud KMS for encrypted key-value storage.
Author-email: Keeper Security <sm@keepersecurity.com>
License: MIT License
Project-URL: Homepage, https://github.com/Keeper-Security/secrets-manager
Project-URL: Documentation, https://docs.keeper.io/secrets-manager/secrets-manager/overview
Project-URL: Repository, https://github.com/Keeper-Security/secrets-manager
Project-URL: Bug Tracker, https://github.com/Keeper-Security/secrets-manager/issues
Keywords: Keeper,Password,Secrets Manager,Storage,GCP,KMS,Google Cloud,Key Management
Classifier: Development Status :: 4 - Beta
Classifier: Intended Audience :: Developers
Classifier: Operating System :: OS Independent
Classifier: Programming Language :: Python
Classifier: Programming Language :: Python :: 3
Classifier: Programming Language :: Python :: 3.6
Classifier: Programming Language :: Python :: 3.7
Classifier: Programming Language :: Python :: 3.8
Classifier: Programming Language :: Python :: 3.9
Classifier: Programming Language :: Python :: 3.10
Classifier: Programming Language :: Python :: 3.11
Classifier: Programming Language :: Python :: 3.12
Classifier: Topic :: Security
Classifier: Topic :: Security :: Cryptography
Requires-Python: >=3.6
License-File: LICENSE
Requires-Dist: keeper-secrets-manager-core>=16.6.6
Requires-Dist: google-cloud-kms>=3.0.0
Requires-Dist: google-crc32c>=1.0.0
Requires-Dist: pycryptodome>=3.15.0
Requires-Dist: requests>=2.25.0
Dynamic: license-file
